pygen_search/__init__.py
pygen_search/config.py
pygen_search/core.py
pygen_search/utils.py
pygen_search-0.1.0.dist-info/licenses/LICENSE
pygen_search-0.1.0.dist-info/METADATA
pygen_search-0.1.0.dist-info/WHEEL
pygen_search-0.1.0.dist-info/top_level.txt
pygen_search-0.1.0.dist-info/RECORD
