Metadata-Version: 2.4
Name: pygen-search
Version: 0.1.0
Summary: A simple and extensible search SDK for Python applications.
Home-page: https://github.com/pygen-labs/pygen-search
Author: PyGen Labs
Author-email: pygen.co@gmail.com
Project-URL: Source, https://github.com/pygen-labs/pygen-search/
Keywords: search,text search,information retrieval,sdk,pygen,search engine library,pygen-search
Classifier: Development Status :: 3 - Alpha
Classifier: Intended Audience :: Developers
Classifier: Topic :: Software Development :: Libraries :: Python Modules
Classifier: Topic :: Text Processing :: Indexing
Classifier: License :: OSI Approved :: MIT License
Classifier: Programming Language :: Python :: 3
Classifier: Programming Language :: Python :: 3.7
Classifier: Programming Language :: Python :: 3.8
Classifier: Programming Language :: Python :: 3.9
Classifier: Programming Language :: Python :: 3.10
Classifier: Programming Language :: Python :: 3.11
Requires-Python: >=3.7
License-File: LICENSE
Dynamic: author
Dynamic: author-email
Dynamic: classifier
Dynamic: description
Dynamic: description-content-type
Dynamic: home-page
Dynamic: keywords
Dynamic: license-file
Dynamic: project-url
Dynamic: requires-python
Dynamic: summary
